Pythoreum/__init__.py
Pythoreum-0.2.1.dist-info/LICENSE.txt
Pythoreum-0.2.1.dist-info/METADATA
Pythoreum-0.2.1.dist-info/WHEEL
Pythoreum-0.2.1.dist-info/top_level.txt
Pythoreum-0.2.1.dist-info/RECORD
