Metadata-Version: 2.1
Name: Pythoreum
Version: 0.2.1
Summary: A simpple Pythogoreus theorum calculator!
Home-page: UNKNOWN
Author: Snehashish Laskar
Author-email: snehashish.laskar@gmail.com
License: UNKNOWN
Platform: UNKNOWN
Classifier: Programming Language :: Python :: 3
Classifier: License :: OSI Approved :: MIT License
Classifier: Operating System :: OS Independent
